[
  {
    "name": "cc",
    "imageUrl": "https://encrypted-tbn0.gstatic.com/images?q=tbn%3AANd9GcRWXDFTonXk2JDFeUHA4nqPrDr1slhbB-NH21xuc0jb_r5LzFG_&usqp=CAU",
    "themeId": "1587650045240",
    "questions": [],
    "creationDate": "2020-04-23T13:54:14.258Z",
    "id": 1587650054276
  },
  {
    "name": "La France",
    "imageUrl": "https://encrypted-tbn0.gstatic.com/images?q=tbn%3AANd9GcQR3zQQ_xBrPG1o3KRD-ZKHGi8kj9aMV8Sncf95aa8oRZ9UuGRm&usqp=CAU",
    "themeId": "1587828592503",
    "questions": [],
    "creationDate": "2020-04-25T15:31:03.136Z",
    "id": 1587828663148
  }
]